GGChat/__init__.py
GGChat/core.py
ggchat-0.1.0.dist-info/METADATA
ggchat-0.1.0.dist-info/WHEEL
ggchat-0.1.0.dist-info/top_level.txt
ggchat-0.1.0.dist-info/RECORD
