Metadata-Version: 2.4
Name: GGChat
Version: 0.1.0
Summary: Графический LLM-чат на Tkinter от OUBStudios.
Author: Твоё имя
Author-email: oubstudios@gmail.com
Classifier: Programming Language :: Python :: 3
Classifier: Operating System :: OS Independent
Requires-Python: >=3.7
Requires-Dist: requests
Dynamic: author
Dynamic: author-email
Dynamic: classifier
Dynamic: description
Dynamic: description-content-type
Dynamic: requires-dist
Dynamic: requires-python
Dynamic: summary
